VBScrambler/VBScrambler.py
VBScrambler-0.1.1.dist-info/LICENSE
VBScrambler-0.1.1.dist-info/METADATA
VBScrambler-0.1.1.dist-info/WHEEL
VBScrambler-0.1.1.dist-info/top_level.txt
VBScrambler-0.1.1.dist-info/RECORD
