Metadata-Version: 2.1
Name: VBScrambler
Version: 0.1.1
Summary: A Python-Based VBScript Code Obfuscator
Author-email: Tim Peck <tim@tjpeck.com>
Project-URL: Homepage, https://github.com/bobby-tablez/VBScrambler
Project-URL: Issues, https://github.com/bobby-tablez/VBScrambler/issues
Keywords: vbscript,obfuscator
Classifier: Programming Language :: Python :: 3
Classifier: License :: OSI Approved :: MIT License
Classifier: Operating System :: OS Independent
Requires-Python: >=3.8
License-File: LICENSE
